Metadata-Version: 2.1
Name: dethub
Version: 0.1.1
Summary: DetHub: Object Detection Model Hub
Home-page: https://github.com/goksenin-uav/dethub
Author: kadirnar
License: MIT
Keywords: machine-learning,deep-learning,ml,pytorch,vision,loss,image-classification,video-classification
Classifier: Development Status :: 5 - Production/Stable
Classifier: Operating System :: OS Independent
Classifier: Intended Audience :: Developers
Classifier: Intended Audience :: Science/Research
Classifier: Programming Language :: Python :: 3
Classifier: Programming Language :: Python :: 3.7
Classifier: Programming Language :: Python :: 3.8
Classifier: Programming Language :: Python :: 3.9
Classifier: Topic :: Software Development :: Libraries
Classifier: Topic :: Software Development :: Libraries :: Python Modules
Classifier: Topic :: Education
Classifier: Topic :: Scientific/Engineering
Classifier: Topic :: Scientific/Engineering :: Artificial Intelligence
Requires-Python: >=3.7
Provides-Extra: tests
Provides-Extra: dev
License-File: LICENSE
